smrpgpatchbuilder/__init__.py
smrpgpatchbuilder/manage.py
smrpgpatchbuilder/datatypes/__init__.py
smrpgpatchbuilder/datatypes/allies/__init__.py
smrpgpatchbuilder/datatypes/allies/ally.py
smrpgpatchbuilder/datatypes/allies/ally_collection.py
smrpgpatchbuilder/datatypes/battle_animation_scripts/__init__.py
smrpgpatchbuilder/datatypes/battle_animation_scripts/types.py
smrpgpatchbuilder/datatypes/battle_animation_scripts/arguments/__init__.py
smrpgpatchbuilder/datatypes/battle_animation_scripts/arguments/battle_targets.py
smrpgpatchbuilder/datatypes/battle_animation_scripts/arguments/bonus_messages.py
smrpgpatchbuilder/datatypes/battle_animation_scripts/arguments/flash_colours.py
smrpgpatchbuilder/datatypes/battle_animation_scripts/arguments/layer_priority_type.py
smrpgpatchbuilder/datatypes/battle_animation_scripts/arguments/mask_effects.py
smrpgpatchbuilder/datatypes/battle_animation_scripts/arguments/message_type.py
smrpgpatchbuilder/datatypes/battle_animation_scripts/arguments/origins.py
smrpgpatchbuilder/datatypes/battle_animation_scripts/arguments/pause_until.py
smrpgpatchbuilder/datatypes/battle_animation_scripts/arguments/shift_type.py
smrpgpatchbuilder/datatypes/battle_animation_scripts/arguments/wave_effect.py
smrpgpatchbuilder/datatypes/battle_animation_scripts/arguments/types/__init__.py
smrpgpatchbuilder/datatypes/battle_animation_scripts/arguments/types/classes.py
smrpgpatchbuilder/datatypes/battle_animation_scripts/commands/__init__.py
smrpgpatchbuilder/datatypes/battle_animation_scripts/commands/commands.py
smrpgpatchbuilder/datatypes/battle_animation_scripts/commands/types/__init__.py
smrpgpatchbuilder/datatypes/battle_animation_scripts/commands/types/classes.py
smrpgpatchbuilder/datatypes/battle_animation_scripts/ids/__init__.py
smrpgpatchbuilder/datatypes/battle_animation_scripts/ids/monster_entrances.py
smrpgpatchbuilder/datatypes/battles/__init__.py
smrpgpatchbuilder/datatypes/battles/battle_dialog_collection.py
smrpgpatchbuilder-1.0.0.dist-info/licenses/LICENSE
smrpgpatchbuilder-1.0.0.dist-info/METADATA
smrpgpatchbuilder-1.0.0.dist-info/WHEEL
smrpgpatchbuilder-1.0.0.dist-info/top_level.txt
smrpgpatchbuilder-1.0.0.dist-info/RECORD
