Metadata-Version: 2.4
Name: smrpgpatchbuilder
Version: 1.0.0
Summary: Patchable base class support for some SMRPG concepts similar to their definitions in Lazy Shell
Author-email: pidgezero_one <s.kischak@gmail.com>
License-Expression: MIT
Project-URL: Homepage, https://github.com/pidgezero-one/smrpgpatchbuilder
Project-URL: Issues, https://github.com/pidgezero-one/smrpgpatchbuilder/issues
Classifier: Programming Language :: Python :: 3
Classifier: Operating System :: OS Independent
Requires-Python: >=3.12
License-File: LICENSE
Requires-Dist: Django==5.1.7
Dynamic: license-file
